promptflow/tools/__init__.py
promptflow/tools/aoai.py
promptflow/tools/aoai_gpt4v.py
promptflow/tools/azure_content_safety.py
promptflow/tools/common.py
promptflow/tools/embedding.py
promptflow/tools/exception.py
promptflow/tools/list.py
promptflow/tools/llm.py
promptflow/tools/llm_vision.py
promptflow/tools/open_model_llm.py
promptflow/tools/openai.py
promptflow/tools/openai_gpt4v.py
promptflow/tools/serpapi.py
promptflow/tools/template_rendering.py
promptflow/tools/yamls/aoai_gpt4v.yaml
promptflow/tools/yamls/azure_content_safety.yaml
promptflow/tools/yamls/embedding.yaml
promptflow/tools/yamls/llm.yaml
promptflow/tools/yamls/llm_vision.yaml
promptflow/tools/yamls/open_model_llm.yaml
promptflow/tools/yamls/openai_gpt4v.yaml
promptflow/tools/yamls/serpapi.yaml
promptflow_tools-1.6.0.dist-info/METADATA
promptflow_tools-1.6.0.dist-info/NOTICE.txt
promptflow_tools-1.6.0.dist-info/WHEEL
promptflow_tools-1.6.0.dist-info/entry_points.txt
promptflow_tools-1.6.0.dist-info/top_level.txt
promptflow_tools-1.6.0.dist-info/RECORD
