Metadata-Version: 2.1
Name: promptflow-tools
Version: 1.6.0
Summary: Prompt flow built-in tools
Home-page: https://github.com/microsoft/promptflow
Author: Microsoft Corporation
Author-email: aml-pt-eng@microsoft.com
Project-URL: Bug Reports, https://github.com/microsoft/promptflow/issues
Project-URL: Source, https://github.com/microsoft/promptflow
Classifier: Programming Language :: Python
Classifier: Programming Language :: Python :: 3
Classifier: Programming Language :: Python :: 3 :: Only
Classifier: Programming Language :: Python :: 3.9
Classifier: Programming Language :: Python :: 3.10
Classifier: Programming Language :: Python :: 3.11
Classifier: License :: OSI Approved :: MIT License
Classifier: Operating System :: OS Independent
Requires-Python: <4.0,>=3.9
License-File: NOTICE.txt
Requires-Dist: google-search-results==2.4.1
Requires-Dist: promptflow>=1.6.0
Requires-Dist: openai>=1.0.0
Provides-Extra: azure
Requires-Dist: azure-mgmt-cognitiveservices==13.5.0; extra == "azure"
